musicviz/__init__.py
musicviz/main.py
musicviz-0.0.5.dist-info/licenses/LICENSE
musicviz-0.0.5.dist-info/METADATA
musicviz-0.0.5.dist-info/WHEEL
musicviz-0.0.5.dist-info/entry_points.txt
musicviz-0.0.5.dist-info/top_level.txt
musicviz-0.0.5.dist-info/RECORD
