Metadata-Version: 2.4
Name: musicviz
Version: 0.0.5
Summary: A really simple music visualization tool.
Home-page: https://github.com/hathibelagal-dev/musicviz
Author: Ashraff Hathibelagal
Project-URL: Source, https://github.com/hathibelagal-dev/musicviz
Project-URL: Tracker, https://github.com/hathibelagal-dev/musicviz/issues
Keywords: music audio visualizer visualization cli videogen video
Classifier: Development Status :: 4 - Beta
Classifier: Intended Audience :: Developers
Classifier: License :: OSI Approved :: Apache Software License
Classifier: Operating System :: OS Independent
Classifier: Programming Language :: Python :: 3.11
Classifier: Programming Language :: Python :: 3.12
Requires-Python: >=3.11
License-File: LICENSE
Requires-Dist: moviepy==1.0.3
Requires-Dist: librosa==0.10.2.post1
Requires-Dist: matplotlib==3.10.3
Requires-Dist: numpy==2.0.2
Dynamic: author
Dynamic: classifier
Dynamic: description
Dynamic: description-content-type
Dynamic: home-page
Dynamic: keywords
Dynamic: license-file
Dynamic: project-url
Dynamic: requires-dist
Dynamic: requires-python
Dynamic: summary
